RCTK/__init__.py
RCTK/core/__init__.py
RCTK/core/data.py
RCTK/core/enums.py
RCTK/core/env.py
RCTK/core/lazy_do.py
RCTK/core/logger.py
RCTK/data/eng.py
RCTK/data/module/__init__.py
RCTK/data/module/link_array.py
RCTK/data/module/mm.py
RCTK/data/module/pool.py
RCTK/io_/__init__.py
RCTK/io_/compress.py
RCTK/io_/file.py
RCTK/runtime/__init__.py
RCTK/runtime/lazy_import.py
RCTK/runtime/py_env.py
RCTK/sys_/__init__.py
RCTK/sys_/base.py
RCTK/sys_/win/__init__.py
RCTK/sys_/win/reg.py
RCTK/sys_/win/sudo.py
RCTK/typing/__init__.py
RCTK/typing/gl.pyi
rc_toolkit-0.2.5.dist-info/WHEEL
rc_toolkit-0.2.5.dist-info/METADATA
rc_toolkit-0.2.5.dist-info/RECORD
