Metadata-Version: 2.1
Name: rc-toolkit
Version: 0.2.5
License: MIT
Author-email: break-soul <57186766+break-soul@users.noreply.github.com>
Requires-Python: >=3.11
Requires-Dist: zstandard>=0.23.0
